[
 {
  "model_accuracy": 19.15219083666683,
  "predicted_class": 0,
  "true_class": 0,
  "features_list": [
   [
    "LSTAT <= 6.99",
    4.983808007408781
   ],
   [
    "6.21 < RM <= 6.62",
    -1.9513054256120814
   ],
   [
    "PTRATIO <= 17.40",
    0.4686770961827196
   ],
   [
    "INDUS <= 4.95",
    0.46498538735580275
   ],
   [
    "279.00 < TAX <= 329.00",
    -0.28930975558273075
   ]
  ]
 },
 {
  "model_accuracy": 19.15219083666683,
  "predicted_class": 0,
  "true_class": 0,
  "features_list": [
   [
    "6.21 < RM <= 6.62",
    -2.085248482320095
   ],
   [
    "6.99 < LSTAT <= 11.23",
    1.536102348321482
   ],
   [
    "0.45 < NOX <= 0.52",
    0.582099046091853
   ],
   [
    "RAD=2",
    -0.5327641086206408
   ],
   [
    "74.85 < AGE <= 93.08",
    -0.522244146991143
   ]
  ]
 },
 {
  "model_accuracy": 19.15219083666683,
  "predicted_class": 0,
  "true_class": 0,
  "features_list": [
   [
    "RM > 6.62",
    8.196117270105914
   ],
   [
    "LSTAT <= 6.99",
    4.746189437925679
   ],
   [
    "TAX <= 279.00",
    0.476494415778931
   ],
   [
    "0.45 < NOX <= 0.52",
    0.4228207285675373
   ],
   [
    "42.27 < AGE <= 74.85",
    0.35528391373723583
   ]
  ]
 },
 {
  "model_accuracy": 19.15219083666683,
  "predicted_class": 0,
  "true_class": 0,
  "features_list": [
   [
    "RM > 6.62",
    8.471689585240174
   ],
   [
    "LSTAT <= 6.99",
    4.957204240175163
   ],
   [
    "DIS > 5.32",
    -0.4799519210604667
   ],
   [
    "TAX <= 279.00",
    0.449851210505048
   ],
   [
    "RAD=3",
    -0.3925140785502427
   ]
  ]
 },
 {
  "model_accuracy": 19.15219083666683,
  "predicted_class": 0,
  "true_class": 0,
  "features_list": [
   [
    "RM > 6.62",
    8.659801220036597
   ],
   [
    "LSTAT <= 6.99",
    4.977281151209567
   ],
   [
    "DIS > 5.32",
    -0.6714389353212956
   ],
   [
    "TAX <= 279.00",
    0.6230880363752965
   ],
   [
    "0.45 < NOX <= 0.52",
    0.3993248517939607
   ]
  ]
 },
 {
  "model_accuracy": 19.15219083666683,
  "predicted_class": 0,
  "true_class": 0,
  "features_list": [
   [
    "LSTAT <= 6.99",
    4.887069353975422
   ],
   [
    "6.21 < RM <= 6.62",
    -2.0300583022246146
   ],
   [
    "DIS > 5.32",
    -0.8521211051030896
   ],
   [
    "CRIM <= 0.72",
    0.2560197884562371
   ],
   [
    "42.27 < AGE <= 74.85",
    0.2295396992683095
   ]
  ]
 },
 {
  "model_accuracy": 19.15219083666683,
  "predicted_class": 0,
  "true_class": 0,
  "features_list": [
   [
    "5.92 < RM <= 6.21",
    -2.566066166491758
   ],
   [
    "11.23 < LSTAT <= 17.17",
    -2.0948881694579407
   ],
   [
    "DIS > 5.32",
    -0.9257461748280188
   ],
   [
    "PTRATIO <= 17.40",
    0.7548839830435317
   ],
   [
    "0.45 < NOX <= 0.52",
    0.5758669415764961
   ]
  ]
 },
 {
  "model_accuracy": 19.15219083666683,
  "predicted_class": 0,
  "true_class": 0,
  "features_list": [
   [
    "LSTAT > 17.17",
    -4.883970630296467
   ],
   [
    "5.92 < RM <= 6.21",
    -2.6342489390015635
   ],
   [
    "PTRATIO <= 17.40",
    0.6005668311254714
   ],
   [
    "0.45 < NOX <= 0.52",
    0.5271371103694404
   ],
   [
    "DIS > 5.32",
    -0.48231259249681757
   ]
  ]
 },
 {
  "model_accuracy": 19.15219083666683,
  "predicted_class": 0,
  "true_class": 0,
  "features_list": [
   [
    "LSTAT > 17.17",
    -4.748333825783012
   ],
   [
    "RM <= 5.92",
    -3.524643583620952
   ],
   [
    "PTRATIO <= 17.40",
    0.5684710638824044
   ],
   [
    "DIS > 5.32",
    -0.48628063336818494
   ],
   [
    "4.95 < INDUS <= 8.56",
    -0.37866335754182806
   ]
  ]
 },
 {
  "model_accuracy": 19.15219083666683,
  "predicted_class": 0,
  "true_class": 0,
  "features_list": [
   [
    "5.92 < RM <= 6.21",
    -2.942783441029605
   ],
   [
    "11.23 < LSTAT <= 17.17",
    -1.8132478483183991
   ],
   [
    "PTRATIO <= 17.40",
    0.8967328453008078
   ],
   [
    "0.45 < NOX <= 0.52",
    0.823295434060118
   ],
   [
    "DIS > 5.32",
    -0.6988315556188305
   ]
  ]
 },
 {
  "model_accuracy": 19.15219083666683,
  "predicted_class": 0,
  "true_class": 0,
  "features_list": [
   [
    "LSTAT > 17.17",
    -4.776128628645961
   ],
   [
    "6.21 < RM <= 6.62",
    -1.922578427793664
   ],
   [
    "PTRATIO <= 17.40",
    0.7115415081195682
   ],
   [
    "0.45 < NOX <= 0.52",
    0.678829016935583
   ],
   [
    "DIS > 5.32",
    -0.41152327014898593
   ]
  ]
 },
 {
  "model_accuracy": 19.15219083666683,
  "predicted_class": 0,
  "true_class": 0,
  "features_list": [
   [
    "5.92 < RM <= 6.21",
    -2.706929486472214
   ],
   [
    "11.23 < LSTAT <= 17.17",
    -1.9012584037308933
   ],
   [
    "DIS > 5.32",
    -0.681533532524592
   ],
   [
    "0.45 < NOX <= 0.52",
    0.42502162438709656
   ],
   [
    "0.72 < CRIM <= 2.25",
    0.37211220975593967
   ]
  ]
 },
 {
  "model_accuracy": 19.15219083666683,
  "predicted_class": 0,
  "true_class": 0,
  "features_list": [
   [
    "RM <= 5.92",
    -3.5711823199034587
   ],
   [
    "11.23 < LSTAT <= 17.17",
    -1.7170094178258795
   ],
   [
    "DIS > 5.32",
    -0.7777674489373245
   ],
   [
    "PTRATIO <= 17.40",
    0.4919952439606384
   ],
   [
    "0.45 < NOX <= 0.52",
    0.4429039024140685
   ]
  ]
 },
 {
  "model_accuracy": 19.15219083666683,
  "predicted_class": 0,
  "true_class": 0,
  "features_list": [
   [
    "5.92 < RM <= 6.21",
    -2.778129448891562
   ],
   [
    "6.99 < LSTAT <= 11.23",
    1.8916548664247077
   ],
   [
    "PTRATIO > 20.20",
    -0.48629279521934377
   ],
   [
    "4.95 < INDUS <= 8.56",
    -0.32130540580293354
   ],
   [
    "RAD=4",
    -0.265112941811904
   ]
  ]
 },
 {
  "model_accuracy": 19.15219083666683,
  "predicted_class": 0,
  "true_class": 0,
  "features_list": [
   [
    "5.92 < RM <= 6.21",
    -2.843971358461542
   ],
   [
    "6.99 < LSTAT <= 11.23",
    1.7316654039825365
   ],
   [
    "PTRATIO > 20.20",
    -0.9756748755964789
   ],
   [
    "2.25 < CRIM <= 32.65",
    -0.45643569308283205
   ],
   [
    "RAD=4",
    -0.45577030335685775
   ]
  ]
 },
 {
  "model_accuracy": 19.15219083666683,
  "predicted_class": 0,
  "true_class": 0,
  "features_list": [
   [
    "RM <= 5.92",
    -3.609357008590289
   ],
   [
    "6.99 < LSTAT <= 11.23",
    1.8410623770779047
   ],
   [
    "PTRATIO > 20.20",
    -0.40697408876645913
   ],
   [
    "RAD=4",
    0.33934593727582235
   ],
   [
    "ZN <= 0.00",
    0.28977302279928124
   ]
  ]
 },
 {
  "model_accuracy": 19.15219083666683,
  "predicted_class": 0,
  "true_class": 0,
  "features_list": [
   [
    "LSTAT <= 6.99",
    4.9483179941874615
   ],
   [
    "5.92 < RM <= 6.21",
    -2.5868883488026575
   ],
   [
    "AGE <= 42.27",
    0.679836977317994
   ],
   [
    "PTRATIO > 20.20",
    -0.3816798504706466
   ],
   [
    "3.39 < DIS <= 5.32",
    -0.26622657212484246
   ]
  ]
 },
 {
  "model_accuracy": 19.15219083666683,
  "predicted_class": 0,
  "true_class": 0,
  "features_list": [
   [
    "5.92 < RM <= 6.21",
    -2.6202656424021424
   ],
   [
    "11.23 < LSTAT <= 17.17",
    -1.8360641815120735
   ],
   [
    "PTRATIO > 20.20",
    -1.273660120186128
   ],
   [
    "4.95 < INDUS <= 8.56",
    -0.28487340371098047
   ],
   [
    "0.52 < NOX <= 0.62",
    0.27194454180721206
   ]
  ]
 },
 {
  "model_accuracy": 19.15219083666683,
  "predicted_class": 0,
  "true_class": 0,
  "features_list": [
   [
    "RM <= 5.92",
    -3.532791269811598
   ],
   [
    "11.23 < LSTAT <= 17.17",
    -1.7886571558405322
   ],
   [
    "PTRATIO > 20.20",
    -0.712743178950963
   ],
   [
    "4.95 < INDUS <= 8.56",
    -0.6239548862999417
   ],
   [
    "AGE <= 42.27",
    0.4074454571997479
   ]
  ]
 },
 {
  "model_accuracy": 19.15219083666683,
  "predicted_class": 0,
  "true_class": 0,
  "features_list": [
   [
    "RM <= 5.92",
    -3.7920406244259084
   ],
   [
    "11.23 < LSTAT <= 17.17",
    -1.8083956329633255
   ],
   [
    "PTRATIO > 20.20",
    -1.0057276157424944
   ],
   [
    "4.95 < INDUS <= 8.56",
    -0.46798435891278584
   ],
   [
    "42.27 < AGE <= 74.85",
    0.40890831295948277
   ]
  ]
 }
]