[{"article":"recidivism-1","word":["Supervised Release = No","Number Prior Arrests = 9","Time Served in Prison = 3 months"]},{"article":"recidivism-2","word":["Prison Violations = Yes"]},{"article":"recidivism-3","word":["Supervised Release = Yes","Alcohol = No","Felony = No","Years School = 12","Prison Violations = No"]},{"article":"recidivism-4","word":["Felony = Yes","Supervised Release = No"]},{"article":"recidivism-5","word":["Alcohol = No","Supervised Release = Yes","Work Release = No","Years School = 10","Time Served in Prison = 23 months"]},{"article":"recidivism-5","word":["Years School = 11","Time Served in Prison = 2 months","Number Prior Arrests = No"]},{"article":"recidivism-5","word":["Number Prior Arrests = No","Supervised Release = Yes","Time Served in Prison = 23 months","Years School = 10"]},{"article":"recidivism-6","word":["Years School = 11","Prison Violations = No","Alcohol = No"]},{"article":"recidivism-7","word":["Alcohol = No","Junky = No","Supervised Release = Yes","Prison Violations = No","Time Served in Prison = 31 months"]},{"article":"recidivism-8","word":["Junky = Yes","Number Prior Arrests = 1","Prison Violations = Yes"]},{"article":"recidivism-9","word":["Felony = Yes","Crime against Person = Yes","Number Prior Arrests = 2","Prison Violations = Yes"]},{"article":"recidivism-10","word":["Time Served in Prison = 53 months"]},{"article":"recidivism-11","word":["Supervised Release = Yes","Prison Violations = No","Number Prior Arrests = No","Crime against Person = No","Crime Against Property = No"]},{"article":"recidivism-12","word":["Supervised Release = Yes","Prison Violations = No","Number Prior Arrests = No"]},{"article":"recidivism-13","word":["Felony = No","Supervised Release = Yes","Prison Violations = No","Number Prior Arrests = No"]},{"article":"recidivism-14","word":["Alcohol = Yes","Number Prior Arrests = 13"]},{"article":"recidivism-15","word":["Prison Violations = No","Number Prior Arrests = No"]},{"article":"recidivism-16","word":["Supervised Release = Yes","Prison Violations = No","Age = 35"]},{"article":"recidivism-17","word":["Felony = Yes","Crime Against Property = Yes","Number Prior Arrests = 3"]},{"article":"recidivism-18","word":["Supervised Release = Yes","Married = Yes","Prison Violations = No","Age = 48"]},{"article":"recidivism-19","word":["Supervised Release = Yes","Years School = 12","Number Prior Arrests = 1","Time Served in Prison = 18 months"]},{"article":"recidivism-19","word":["Supervised Release = No","Alcohol = Yes"]}]