[
 {
  "model_accuracy": 0.862,
  "predicted_class": "med",
  "true_class": "med",
  "predictions_weights": [
   [
    0.078,
    0.174,
    0.584,
    0.078,
    0.086
   ]
  ],
  "features_list": [
   [
    "doctor",
    0.10344348607730385
   ],
   [
    "symptoms",
    0.04493770997980929
   ],
   [
    "pain",
    0.04252695020787641
   ],
   [
    "she",
    0.03961097311211674
   ],
   [
    "medicine",
    0.03550927562986577
   ],
   [
    "My",
    0.024954676079287075
   ],
   [
    "cancer",
    0.02022055086082933
   ],
   [
    "her",
    0.019475466384131872
   ],
   [
    "device",
    -0.017236047590884658
   ],
   [
    "line",
    -0.01208256298038664
   ]
  ]
 },
 {
  "model_accuracy": 0.862,
  "predicted_class": "med",
  "true_class": "med",
  "predictions_weights": [
   [
    0.152,
    0.192,
    0.53,
    0.078,
    0.048
   ]
  ],
  "features_list": [
   [
    "she",
    0.07067956971666133
   ],
   [
    "symptoms",
    0.059021241596996565
   ],
   [
    "pain",
    0.058595148610376686
   ],
   [
    "My",
    0.04057546602420838
   ],
   [
    "her",
    0.03267258123771645
   ],
   [
    "is",
    0.024486623999166797
   ],
   [
    "She",
    0.02058529220589189
   ],
   [
    "to",
    0.016642935319631902
   ],
   [
    "been",
    0.014906849734933536
   ],
   [
    "has",
    0.014443745177009155
   ]
  ]
 },
 {
  "model_accuracy": 0.862,
  "predicted_class": "med",
  "true_class": "med",
  "predictions_weights": [
   [
    0.124,
    0.19,
    0.468,
    0.144,
    0.074
   ]
  ],
  "features_list": [
   [
    "medical",
    0.1023974062304687
   ],
   [
    "of",
    0.030995141776796385
   ],
   [
    "not",
    0.0276183985785621
   ],
   [
    "severe",
    0.02697958748609709
   ],
   [
    "infection",
    0.02604430055548295
   ],
   [
    "taking",
    0.024834858541878658
   ],
   [
    "in",
    0.01683397984837618
   ],
   [
    "Medicine",
    0.016530575336270687
   ],
   [
    "sci",
    -0.012647665062239894
   ],
   [
    "new",
    -0.005847974515830806
   ]
  ]
 },
 {
  "model_accuracy": 0.862,
  "predicted_class": "med",
  "true_class": "med",
  "predictions_weights": [
   [
    0.136,
    0.208,
    0.438,
    0.124,
    0.094
   ]
  ],
  "features_list": [
   [
    "effects",
    0.05224271539350741
   ],
   [
    "studies",
    0.027680938737042086
   ],
   [
    "Is",
    0.02596935019007421
   ],
   [
    "taking",
    0.024085612220089717
   ],
   [
    "of",
    0.021424357299495544
   ],
   [
    "is",
    0.02131227672287988
   ],
   [
    "infection",
    0.021115346253616975
   ],
   [
    "infections",
    0.014635736407687084
   ],
   [
    "illness",
    0.01314479080551884
   ],
   [
    "build",
    -0.01295470393641791
   ]
  ]
 },
 {
  "model_accuracy": 0.862,
  "predicted_class": "electronics",
  "true_class": "med",
  "predictions_weights": [
   [
    0.154,
    0.42,
    0.212,
    0.16,
    0.054
   ]
  ],
  "features_list": [
   [
    "use",
    0.07218539361270741
   ],
   [
    "people",
    -0.049068073599476514
   ],
   [
    "In",
    -0.032949653983286316
   ],
   [
    "Re",
    -0.029565998207745577
   ],
   [
    "writes",
    -0.02715834650957525
   ],
   [
    "article",
    -0.02399897395207677
   ],
   [
    "eiu",
    0.023630061103671923
   ],
   [
    "build",
    0.021499136603653414
   ],
   [
    "ux1",
    0.01913548328252267
   ],
   [
    "cts",
    0.014348666703622118
   ]
  ]
 },
 {
  "model_accuracy": 0.862,
  "predicted_class": "med",
  "true_class": "med",
  "predictions_weights": [
   [
    0.16,
    0.184,
    0.402,
    0.146,
    0.108
   ]
  ],
  "features_list": [
   [
    "medical",
    0.09109092216053798
   ],
   [
    "treatment",
    0.07981773735910193
   ],
   [
    "of",
    0.023641633780340295
   ],
   [
    "not",
    0.01522592910747127
   ],
   [
    "and",
    0.014932635545738477
   ],
   [
    "case",
    0.011369020362193052
   ],
   [
    "just",
    -0.010188962831985818
   ],
   [
    "assault",
    -0.00976719372199244
   ],
   [
    "in",
    0.009733116228369133
   ],
   [
    "would",
    -0.008030766683188511
   ]
  ]
 },
 {
  "model_accuracy": 0.862,
  "predicted_class": "med",
  "true_class": "med",
  "predictions_weights": [
   [
    0.138,
    0.142,
    0.43,
    0.134,
    0.156
   ]
  ],
  "features_list": [
   [
    "medical",
    0.08721713183927982
   ],
   [
    "treatment",
    0.06902048128975467
   ],
   [
    "of",
    0.01762856473437937
   ],
   [
    "reaction",
    0.014158214908684946
   ],
   [
    "Medicine",
    0.012694195739347687
   ],
   [
    "soon",
    0.012239290346666123
   ],
   [
    "assault",
    -0.01211596699375216
   ],
   [
    "cause",
    0.011537434075580695
   ],
   [
    "them",
    -0.01071456082903852
   ],
   [
    "case",
    0.01046586368429255
   ]
  ]
 },
 {
  "model_accuracy": 0.862,
  "predicted_class": "med",
  "true_class": "med",
  "predictions_weights": [
   [
    0.1,
    0.286,
    0.354,
    0.174,
    0.086
   ]
  ],
  "features_list": [
   [
    "medical",
    0.10146885388498837
   ],
   [
    "of",
    0.027650068612851384
   ],
   [
    "literature",
    0.024464492163302334
   ],
   [
    "infection",
    0.020062851431149362
   ],
   [
    "is",
    0.016505888951204833
   ],
   [
    "in",
    0.0145171328727347
   ],
   [
    "compound",
    -0.012575526071353975
   ],
   [
    "Lines",
    -0.010555547092590238
   ],
   [
    "project",
    -0.01017188683168078
   ],
   [
    "not",
    0.006535155417673795
   ]
  ]
 },
 {
  "model_accuracy": 0.862,
  "predicted_class": "med",
  "true_class": "med",
  "predictions_weights": [
   [
    0.12,
    0.086,
    0.61,
    0.074,
    0.11
   ]
  ],
  "features_list": [
   [
    "MSG",
    0.07584986652290089
   ],
   [
    "superstition",
    0.0725627698554336
   ],
   [
    "sensitivity",
    0.06897670864657696
   ],
   [
    "food",
    0.05020657525732051
   ],
   [
    "studies",
    0.024765739831375994
   ],
   [
    "that",
    0.022597426733107582
   ],
   [
    "Is",
    0.02152517365096202
   ],
   [
    "My",
    0.0203405749772117
   ],
   [
    "is",
    0.019460859723397318
   ],
   [
    "my",
    0.01754803727560774
   ]
  ]
 },
 {
  "model_accuracy": 0.862,
  "predicted_class": "autos",
  "true_class": "med",
  "predictions_weights": [
   [
    0.318,
    0.192,
    0.31,
    0.122,
    0.058
   ]
  ],
  "features_list": [
   [
    "Lines",
    0.03763370645381938
   ],
   [
    "Organization",
    0.02954644810919456
   ],
   [
    "Distribution",
    0.028806042469168784
   ],
   [
    "Subject",
    0.028013036438517706
   ],
   [
    "be",
    -0.02494676411607054
   ],
   [
    "to",
    -0.02175965235053383
   ],
   [
    "From",
    0.02023406997871714
   ],
   [
    "can",
    -0.014388283618944037
   ],
   [
    "about",
    0.011633720613212746
   ],
   [
    "com",
    0.011264465738215847
   ]
  ]
 }
]